setup.cfg
setup.py
py_sak/__init__.py
py_sak/validation.py
py_sak.egg-info/PKG-INFO
py_sak.egg-info/SOURCES.txt
py_sak.egg-info/dependency_links.txt
py_sak.egg-info/requires.txt
py_sak.egg-info/top_level.txt