Metadata-Version: 1.1
Name: py-sak
Version: 0.1
Summary: Python Swiss Army Knife: common utilities and helpers for boilerplate code
Home-page: https://github.com/marccarre/py_sak
Author: Marc CARRE
Author-email: carre.marc@gmail.com
License: UNKNOWN
Download-URL: https://github.com/marccarre/py_sak/tarball/0.1
Keywords: common,utilities,utility,utils,util,helpers,helper,input validation,validation
Platform: UNKNOWN
